forager_service/__init__.py
forager_service/app_services/__init__.py
forager_service/app_services/async_service.py
forager_service/app_services/crud_service.py
forager_service/app_services/service.py
forager_service/common/__init__.py
forager_service/common/common_utilities.py
forager_service/common/exceptions.py
forager_service/common/validators.py
forager_service/hunter.py
forager_service/operation_handlers/__init__.py
forager_service/operation_handlers/email_verify_record_handler.py
forager_service-0.1.2.dist-info/LICENSE
forager_service-0.1.2.dist-info/METADATA
forager_service-0.1.2.dist-info/WHEEL
forager_service-0.1.2.dist-info/RECORD
